openllm_client/__init__.py
openllm_client/__init__.pyi
openllm_client/_http.py
openllm_client/_schemas.py
openllm_client/_shim.py
openllm_client/_stream.py
openllm_client/_typing_compat.py
openllm_client/_version.py
openllm_client/py.typed
openllm_client-0.5.7.dist-info/METADATA
openllm_client-0.5.7.dist-info/WHEEL
openllm_client-0.5.7.dist-info/licenses/LICENSE.md
openllm_client-0.5.7.dist-info/RECORD
