Metadata-Version: 2.1
Name: openllm-client
Version: 0.5.7
Summary: OpenLLM Client: Interacting with OpenLLM HTTP/gRPC server, or any BentoML server.
Project-URL: Blog, https://modelserving.com
Project-URL: Chat, https://l.bentoml.com/join-openllm-discord
Project-URL: Documentation, https://github.com/bentoml/OpenLLM/blob/main/openllm-client/README.md
Project-URL: GitHub, https://github.com/bentoml/OpenLLM/blob/main/openllm-client
Project-URL: History, https://github.com/bentoml/OpenLLM/blob/main/CHANGELOG.md
Project-URL: Homepage, https://bentoml.com
Project-URL: Tracker, https://github.com/bentoml/OpenLLM/issues
Project-URL: Twitter, https://twitter.com/bentomlai
Author-email: Aaron Pham <aarnphm@bentoml.com>, BentoML Team <contact@bentoml.com>
License-Expression: Apache-2.0
License-File: LICENSE.md
Keywords: AI,Alpaca,BentoML,Falcon,Fine tuning,Generative AI,LLMOps,Large Language Model,Llama 2,MLOps,Model Deployment,Model Serving,PyTorch,Serverless,StableLM,Transformers,Vicuna
Classifier: Development Status :: 4 - Beta
Classifier: Intended Audience :: Developers
Classifier: Intended Audience :: Science/Research
Classifier: Intended Audience :: System Administrators
Classifier: License :: OSI Approved :: Apache Software License
Classifier: Operating System :: OS Independent
Classifier: Programming Language :: Python
Classifier: Programming Language :: Python :: 3
Classifier: Programming Language :: Python :: 3 :: Only
Classifier: Programming Language :: Python :: 3.8
Classifier: Programming Language :: Python :: 3.9
Classifier: Programming Language :: Python :: 3.10
Classifier: Programming Language :: Python :: 3.11
Classifier: Programming Language :: Python :: Implementation :: CPython
Classifier: Programming Language :: Python :: Implementation :: PyPy
Classifier: Topic :: Scientific/Engineering
Classifier: Topic :: Software Development :: Libraries
Classifier: Typing :: Typed
Requires-Python: >=3.8
Requires-Dist: anyio
Requires-Dist: distro
Requires-Dist: httpx
Requires-Dist: openllm-core
Provides-Extra: agents
Requires-Dist: diffusers; extra == 'agents'
Requires-Dist: soundfile; extra == 'agents'
Requires-Dist: transformers[agents]>=4.30; extra == 'agents'
Provides-Extra: auth
Requires-Dist: httpx-auth; extra == 'auth'
Provides-Extra: full
Requires-Dist: openllm-client[agents,auth,grpc]; extra == 'full'
Provides-Extra: grpc
Requires-Dist: bentoml[grpc]<1.2,>=1.1.11; extra == 'grpc'
